.gitignore
CHANGELOG.rst
CONTRIBUTORS.rst
LICENSE
MANIFEST.in
README
build.py
setup.py
demos/chat/client.pyw
demos/chat/readme.txt
demos/chat/server.py
demos/filemon/client.py
demos/filemon/readme.txt
demos/filemon/server.py
demos/rpycfs/mount.rpycfs.py
demos/rpycfs/readme.txt
demos/rpycfs/rpycfsd.py
demos/rpycfs/service.py
demos/time/client.py
demos/time/readme.txt
demos/time/server.py
demos/time/time_service.py
demos/web8/client.pyw
demos/web8/readme.txt
demos/web8/safegtk.py
demos/web8/server.py
issues/issue14.py
issues/issue26.py
issues/issue32.py
issues/issue8_client.py
issues/issue8_server.py
issues/issue8_test.py
issues/issue44/cert.crt
issues/issue44/cert.key
issues/issue44/nonrpyc_client.py
issues/issue44/nonrpyc_server.py
issues/issue44/rpyc_client.py
issues/issue44/rpyc_server.py
rpyc/__init__.py
rpyc/version.py
rpyc/core/__init__.py
rpyc/core/async.py
rpyc/core/brine.py
rpyc/core/channel.py
rpyc/core/consts.py
rpyc/core/netref.py
rpyc/core/protocol.py
rpyc/core/service.py
rpyc/core/stream.py
rpyc/core/vinegar.py
rpyc/lib/__init__.py
rpyc/lib/colls.py
rpyc/lib/compat.py
rpyc/scripts/rpyc_classic.py
rpyc/scripts/rpyc_registry.py
rpyc/utils/__init__.py
rpyc/utils/authenticators.py
rpyc/utils/classic.py
rpyc/utils/factory.py
rpyc/utils/helpers.py
rpyc/utils/registry.py
rpyc/utils/server.py
rpyc/utils/ssh.py
rpyc_op.egg-info/PKG-INFO
rpyc_op.egg-info/SOURCES.txt
rpyc_op.egg-info/dependency_links.txt
rpyc_op.egg-info/top_level.txt
site/.gitignore
site/Makefile
site/TODO.txt
site/api.rst
site/changelog.rst
site/conf.py
site/docs.rst
site/index.rst
site/install.rst
site/make.bat
site/screencasts.rst
site/tutorial.rst
site/_static/facebook-logo.png
site/_static/fish-text-black.png
site/_static/fish-text-white.png
site/_static/fish-text.png
site/_static/fish2.png
site/_static/github-logo.png
site/_static/rpyc-banner.png
site/_static/rpyc3-logo-big.png
site/_static/rpyc3-logo-medium.png
site/_static/rpyc3-logo-tiny.ico
site/_static/rpyc3-logo-tiny.png
site/_static/rpyc3-logo.ppt
site/_static/screenshot.png
site/_themes/agogo2/layout.html
site/_themes/agogo2/theme.conf
